recollection/__init__.py
recollection/compat.py
recollection/constants.py
recollection/core.py
recollection/exceptions.py
recollection/infer.py
recollection/inference.py
recollection/serialiser.py
recollection/signal.py
recollection/examples/__init__.py
recollection/examples/boardgame/__init__.py
recollection/examples/boardgame/game.py
recollection/examples/pins/__init__.py
recollection/examples/pins/demo.py
recollection/examples/renamer/__init__.py
recollection/examples/renamer/demo.py
recollection/examples/userprefs/__init__.py
recollection/examples/userprefs/demo.py
recollection/serialisers/__init__.py
recollection/serialisers/appdata.py
recollection/serialisers/picklefile.py
recollection/tests/__init__.py
recollection/tests/classes.py
recollection/tests/test_inference.py
recollection/tests/test_memento.py
recollection/tests/test_serialise_appdata.py
recollection/tests/test_serialse_pickle.py
recollection-0.9.3.dist-info/LICENSE
recollection-0.9.3.dist-info/METADATA
recollection-0.9.3.dist-info/WHEEL
recollection-0.9.3.dist-info/top_level.txt
recollection-0.9.3.dist-info/RECORD
