Metadata-Version: 2.1
Name: recollection
Version: 0.9.3
Summary: A python package exposing the memento design pattern
Home-page: https://github.com/mikemalinowski/recollection
Author: Mike Malinowski
Author-email: mike@twisted.space
License: UNKNOWN
Keywords: recollect recollection memento mementos
Platform: UNKNOWN
Classifier: Programming Language :: Python
Classifier: License :: OSI Approved :: MIT License
Classifier: Operating System :: OS Independent
Requires-Dist: six
